nigga/__init__.py
nxggas-0.0.1.dist-info/METADATA
nxggas-0.0.1.dist-info/WHEEL
nxggas-0.0.1.dist-info/top_level.txt
nxggas-0.0.1.dist-info/RECORD
