Metadata-Version: 2.1
Name: nxggas
Version: 0.0.1
Summary: My First Package
Author: Vardxg
Author-email: <vardxgend@gmail.com>
Keywords: python
Classifier: Development Status :: 1 - Planning
Classifier: Intended Audience :: Developers
Classifier: Programming Language :: Python :: 3
Classifier: Operating System :: Unix
Classifier: Operating System :: MacOS :: MacOS X
Classifier: Operating System :: Microsoft :: Windows
Requires-Dist: pystyle
